CHANGELOG.rst
LICENSE
MANIFEST.in
README.rst
requirements.txt
setup.cfg
setup.py
src/__init__.py
src/pasttle/__init__.py
src/pasttle/model.py
src/pasttle/server.py
src/pasttle/util.py
src/pasttle.egg-info/PKG-INFO
src/pasttle.egg-info/SOURCES.txt
src/pasttle.egg-info/dependency_links.txt
src/pasttle.egg-info/entry_points.txt
src/pasttle.egg-info/not-zip-safe
src/pasttle.egg-info/pbr.json
src/pasttle.egg-info/requires.txt
src/pasttle.egg-info/top_level.txt
src/pasttle/views/base.html
src/pasttle/views/index.html
src/pasttle/views/password_protect.html
src/pasttle/views/post.html
src/pasttle/views/pygmentize.html
src/pasttle/views/recent.html
src/pasttle/views/css/style.css
src/pasttle/views/images/icon.png