Metadata-Version: 1.1
Name: pasttle
Version: 0.10.0
Summary: Simple pastebin on top of bottle.
Home-page: https://github.com/thekad/pasttle
Author: Jorge Gallegos
Author-email: kad@blegh.net
License: MIT
Keywords: pastebin,web,paste,bottlepy
Platform: any
Classifier: Programming Language :: Python :: 3.5
Classifier: Programming Language :: Python :: 3.6
Classifier: Programming Language :: Python :: 3.7
Classifier: Programming Language :: Python :: 3.8
Classifier: Development Status :: 4 - Beta
Classifier: Environment :: Console
Classifier: Environment :: Web Environment
Classifier: Intended Audience :: Developers
Classifier: License :: OSI Approved :: MIT License
Classifier: Operating System :: OS Independent
Classifier: Topic :: Internet :: WWW/HTTP :: Dynamic Content
Classifier: Topic :: Software Development :: Libraries :: Python Modules
